{
  "project_info": {
    "project_number": "843267668371",
    "project_id": "working-hours-8dad9",
    "storage_bucket": "working-hours-8dad9.appspot.com"
  },
  "client": [
    {
      "client_info": {
        "mobilesdk_app_id": "1:843267668371:android:3eacfd6808d253835c1066",
        "android_client_info": {
          "package_name": "com.example.working_hours"
        }
      },
      "oauth_client": [],
      "api_key": [
        {
          "current_key": "AIzaSyAmlpm9dR7uh8HTtv9apV6GFgGVS4QApNQ"
        }
      ],
      "services": {
        "appinvite_service": {
          "other_platform_oauth_client": []
        }
      }
    }
  ],
  "configuration_version": "1"
}